jinja2_s3loader/__about__.py
jinja2_s3loader/__init__.py
jinja2_s3loader-0.3.0.dist-info/DESCRIPTION.rst
jinja2_s3loader-0.3.0.dist-info/METADATA
jinja2_s3loader-0.3.0.dist-info/metadata.json
jinja2_s3loader-0.3.0.dist-info/RECORD
jinja2_s3loader-0.3.0.dist-info/top_level.txt
jinja2_s3loader-0.3.0.dist-info/WHEEL
