Metadata-Version: 1.1
Name: jinja2_s3loader
Version: 0.3.0
Summary: A Jinja2 template loader for AWS S3.
Home-page: https://github.com/veselosky/jinja2_s3loader
Author: Vince Veselosky
Author-email: vince@veselosky.com
License: Apache 2.0
Platform: UNKNOWN
Classifier: Development Status :: 2 - Pre-Alpha
Classifier: Intended Audience :: Developers
Classifier: License :: OSI Approved :: Apache Software License
Classifier: Natural Language :: English
Classifier: Programming Language :: Python :: 2
Classifier: Programming Language :: Python :: 2.6
Classifier: Programming Language :: Python :: 2.7
Classifier: Programming Language :: Python :: 3
Classifier: Programming Language :: Python :: 3.4
